batchscanner/__init__.py
batchscanner/__main__.py
batchscanner/batchscan.py
batchscanner/config.toml
batchscanner/credentials.py
batchscanner/network.txt
batchscanner/script.txt
batchscanner/sikcli.py
batchscanner/sikcommander.py
batchscanner/sikssh_config.toml
batchscanner/parsers/__init__.py
batchscanner/parsers/parse_show_eh.py
batchscanner/parsers/parse_show_tg.py
bachscanner_siklu-0.1.1.dist-info/LICENCE
bachscanner_siklu-0.1.1.dist-info/METADATA
bachscanner_siklu-0.1.1.dist-info/WHEEL
bachscanner_siklu-0.1.1.dist-info/entry_points.txt
bachscanner_siklu-0.1.1.dist-info/top_level.txt
bachscanner_siklu-0.1.1.dist-info/RECORD
