Metadata-Version: 2.1
Name: bachscanner-siklu
Version: 0.1.1
Summary: Batch-query/configure multiple Siklu radios via their CLI (SSH) interface
Author-email: Daniel Ephraty <daniel@ephraty.com>
License: MIT License
Project-URL: repository, https://github.com/DanielEphraty/batchscanner
Project-URL: documentation, https://batchscanner.readthedocs.io/en/latest/
Keywords: cli,batch,siklu,siklu radios
Classifier: License :: OSI Approved :: MIT License
Classifier: Programming Language :: Python
Classifier: Programming Language :: Python :: 3
Requires-Python: >=3.11
License-File: LICENCE
Requires-Dist: paramiko
Requires-Dist: pyyaml
Requires-Dist: tabulate
Provides-Extra: build
Requires-Dist: build ; extra == 'build'
Requires-Dist: twine ; extra == 'build'
Provides-Extra: dev
Requires-Dist: sphinx-rtd-theme ; extra == 'dev'
